pysmali-0.2.8.dist-info/licenses/LICENSE
smali/__init__.py
smali/base.py
smali/opcode.py
smali/reader.py
smali/visitor.py
smali/writer.py
smali/bridge/__init__.py
smali/bridge/errors.py
smali/bridge/executor.py
smali/bridge/frame.py
smali/bridge/lang.py
smali/bridge/objects.py
smali/bridge/vm.py
smali/shell/__init__.py
smali/shell/__main__.py
smali/shell/cli.py
smali/shell/model.py
pysmali-0.2.8.dist-info/METADATA
pysmali-0.2.8.dist-info/WHEEL
pysmali-0.2.8.dist-info/entry_points.txt
pysmali-0.2.8.dist-info/top_level.txt
pysmali-0.2.8.dist-info/RECORD
