Metadata-Version: 2.4
Name: pysmali
Version: 0.2.8
Summary: Smali Visitor-API and Smali emulator
Author-email: MatrixEditor <not@supported.com>
Project-URL: Homepage, https://github.com/MatrixEditor/pysmali
Project-URL: API-Docs, https://matrixeditor.github.io/pysmali/
Classifier: Development Status :: 5 - Production/Stable
Classifier: Intended Audience :: Science/Research
Classifier: License :: OSI Approved :: GNU General Public License v3 (GPLv3)
Classifier: Programming Language :: Python :: 3.9
Classifier: Programming Language :: Python :: 3.10
License-File: LICENSE
Dynamic: license-file
